{
  "v": "5.5.9",
  "fr": 29.9700012207031,
  "ip": 0,
  "op": 59.0000024031193,
  "w": 25,
  "h": 25,
  "nm": "Comp 1",
  "ddd": 0,
  "assets": [],
  "layers": [
    {
      "ddd": 0,
      "ind": 25,
      "ty": 4,
      "nm": "Layer 24 Outlines",
      "sr": 1,
      "ks": {
        "o": {
          "a": 0,
          "k": 100,
          "ix": 11
        },
        "r": {
          "a": 0,
          "k": 0,
          "ix": 10
        },
        "p": {
          "a": 0,
          "k": [
            15.902,
            12.523,
            0
          ],
          "ix": 2,
          "x": "var $bm_rt;\nvar amp, freq, decay, n, n, t, t, v;\ntry {\n    amp = $bm_div(effect('Elastic Controller 2')(1), 200);\n    freq = $bm_div(effect('Elastic Controller 2')(2), 30);\n    decay = $bm_div(effect('Elastic Controller 2')(3), 10);\n    $bm_rt = n = 0;\n    if (numKeys > 0) {\n        $bm_rt = n = nearestKey(time).index;\n        if (key(n).time > time) {\n            n--;\n        }\n    }\n    if (n == 0) {\n        $bm_rt = t = 0;\n    } else {\n        $bm_rt = t = $bm_sub(time, key(n).time);\n    }\n    if (n > 0) {\n        v = velocityAtTime($bm_sub(key(n).time, $bm_div(thisComp.frameDuration, 10)));\n        $bm_rt = $bm_sum(value, $bm_div($bm_mul($bm_mul(v, amp), Math.sin($bm_mul($bm_mul($bm_mul(freq, t), 2), Math.PI))), Math.exp($bm_mul(decay, t))));\n    } else {\n        $bm_rt = value;\n    }\n} catch (e$$4) {\n    $bm_rt = value = value;\n}"
        },
        "a": {
          "a": 0,
          "k": [
            11.5,
            11.5,
            0
          ],
          "ix": 1
        },
        "s": {
          "a": 0,
          "k": [
            73.569,
            73.569,
            100
          ],
          "ix": 6
        }
      },
      "ao": 0,
      "ef": [
        {
          "ty": 5,
          "nm": "Elastic Controller",
          "np": 5,
          "mn": "Pseudo/MDS Elastic Controller",
          "ix": 1,
          "en": 1,
          "ef": [
            {
              "ty": 0,
              "nm": "Amplitude",
              "mn": "Pseudo/MDS Elastic Controller-0001",
              "ix": 1,
              "v": {
                "a": 0,
                "k": 20,
                "ix": 1
              }
            },
            {
              "ty": 0,
              "nm": "Frequency",
              "mn": "Pseudo/MDS Elastic Controller-0002",
              "ix": 2,
              "v": {
                "a": 0,
                "k": 40,
                "ix": 2
              }
            },
            {
              "ty": 0,
              "nm": "Decay",
              "mn": "Pseudo/MDS Elastic Controller-0003",
              "ix": 3,
              "v": {
                "a": 0,
                "k": 60,
                "ix": 3
              }
            }
          ]
        }
      ],
      "shapes": [
        {
          "ty": "gr",
          "it": [
            {
              "ty": "gr",
              "it": [
                {
                  "ind": 0,
                  "ty": "sh",
                  "ix": 1,
                  "ks": {
                    "a": 0,
                    "k": {
                      "i": [
                        [
                          -0.552,
                          0
                        ],
                        [
                          0,
                          0.552
                        ],
                        [
                          0.552,
                          0
                        ],
                        [
                          0,
                          -0.552
                        ]
                      ],
                      "o": [
                        [
                          0.552,
                          0
                        ],
                        [
                          0,
                          -0.552
                        ],
                        [
                          -0.552,
                          0
                        ],
                        [
                          0,
                          0.552
                        ]
                      ],
                      "v": [
                        [
                          0,
                          1
                        ],
                        [
                          1,
                          0
                        ],
                        [
                          0,
                          -1
                        ],
                        [
                          -1,
                          0
                        ]
                      ],
                      "c": true
                    },
                    "ix": 2
                  },
                  "nm": "Path 1",
                  "mn": "ADBE Vector Shape - Group",
                  "hd": false
                },
                {
                  "ty": "st",
                  "c": {
                    "a": 0,
                    "k": [
                      1,
                      1,
                      1,
                      1
                    ],
                    "ix": 3
                  },
                  "o": {
                    "a": 0,
                    "k": 100,
                    "ix": 4
                  },
                  "w": {
                    "a": 0,
                    "k": 1.5,
                    "ix": 5
                  },
                  "lc": 2,
                  "lj": 2,
                  "bm": 0,
                  "nm": "Stroke 1",
                  "mn": "ADBE Vector Graphic - Stroke",
                  "hd": false
                },
                {
                  "ty": "tr",
                  "p": {
                    "a": 0,
                    "k": [
                      5.5,
                      17.5
                    ],
                    "ix": 2
                  },
                  "a": {
                    "a": 0,
                    "k": [
                      0,
                      0
                    ],
                    "ix": 1
                  },
                  "s": {
                    "a": 0,
                    "k": [
                      100,
                      100
                    ],
                    "ix": 3
                  },
                  "r": {
                    "a": 0,
                    "k": 0,
                    "ix": 6
                  },
                  "o": {
                    "a": 0,
                    "k": 100,
                    "ix": 7
                  },
                  "sk": {
                    "a": 0,
                    "k": 0,
                    "ix": 4
                  },
                  "sa": {
                    "a": 0,
                    "k": 0,
                    "ix": 5
                  },
                  "nm": "Transform"
                }
              ],
              "nm": "Group 1",
              "np": 2,
              "cix": 2,
              "bm": 0,
              "ix": 1,
              "mn": "ADBE Vector Group",
              "hd": false
            },
            {
              "ty": "gr",
              "it": [
                {
                  "ind": 0,
                  "ty": "sh",
                  "ix": 1,
                  "ks": {
                    "a": 1,
                    "k": [
                      {
                        "i": {
                          "x": 0.65,
                          "y": 1
                        },
                        "o": {
                          "x": 0.35,
                          "y": 0
                        },
                        "t": 8.391,
                        "s": [
                          {
                            "i": [
                              [
                                1.06,
                                -1.06
                              ],
                              [
                                0,
                                0
                              ],
                              [
                                0,
                                0
                              ],
                              [
                                0,
                                1.08
                              ],
                              [
                                0,
                                0
                              ],
                              [
                                0,
                                0
                              ],
                              [
                                -1.06,
                                -1.06
                              ],
                              [
                                0,
                                0
                              ]
                            ],
                            "o": [
                              [
                                0,
                                0
                              ],
                              [
                                0,
                                0
                              ],
                              [
                                0.7,
                                -0.72
                              ],
                              [
                                0,
                                0
                              ],
                              [
                                0,
                                0
                              ],
                              [
                                1.06,
                                -1.06
                              ],
                              [
                                0,
                                0
                              ],
                              [
                                1.06,
                                1.06
                              ]
                            ],
                            "v": [
                              [
                                4.225,
                                -1.39
                              ],
                              [
                                1.515,
                                1.32
                              ],
                              [
                                -5.285,
                                8.11
                              ],
                              [
                                -4.145,
                                5.32
                              ],
                              [
                                -4.145,
                                -4.34
                              ],
                              [
                                -1.435,
                                -7.05
                              ],
                              [
                                2.105,
                                -7.05
                              ],
                              [
                                4.225,
                                -4.93
                              ]
                            ],
                            "c": true
                          }
                        ]
                      },
                      {
                        "i": {
                          "x": 0.65,
                          "y": 1
                        },
                        "o": {
                          "x": 0.35,
                          "y": 0
                        },
                        "t": 20.38,
                        "s": [
                          {
                            "i": [
                              [
                                0.584,
                                -1.374
                              ],
                              [
                                0,
                                0
                              ],
                              [
                                0,
                                0
                              ],
                              [
                                0,
                                1.08
                              ],
                              [
                                0,
                                0
                              ],
                              [
                                0,
                                0
                              ],
                              [
                                -1.277,
                                -0.482
                              ],
                              [
                                0,
                                0
                              ]
                            ],
                            "o": [
                              [
                                0,
                                0
                              ],
                              [
                                0,
                                0
                              ],
                              [
                                0.7,
                                -0.72
                              ],
                              [
                                0,
                                0
                              ],
                              [
                                0,
                                0
                              ],
                              [
                                0.364,
                                -1.454
                              ],
                              [
                                0,
                                0
                              ],
                              [
                                1.277,
                                0.482
                              ]
                            ],
                            "v": [
                              [
                                2.465,
                                -5.183
                              ],
                              [
                                -0.568,
                                0.78
                              ],
                              [
                                -5.285,
                                8.11
                              ],
                              [
                                -4.145,
                                5.32
                              ],
                              [
                                -4.15,
                                -3.44
                              ],
                              [
                                -4.107,
                                -7.196
                              ],
                              [
                                -1.347,
                                -9.483
                              ],
                              [
                                1.309,
                                -8.282
                              ]
                            ],
                            "c": true
                          }
                        ]
                      },
                      {
                        "t": 29.9700012207031,
                        "s": [
                          {
                            "i": [
                              [
                                1.06,
                                -1.06
                              ],
                              [
                                0,
                                0
                              ],
                              [
                                0,
                                0
                              ],
                              [
                                0,
                                1.08
                              ],
                              [
                                0,
                                0
                              ],
                              [
                                0,
                                0
                              ],
                              [
                                -1.06,
                                -1.06
                              ],
                              [
                                0,
                                0
                              ]
                            ],
                            "o": [
                              [
                                0,
                                0
                              ],
                              [
                                0,
                                0
                              ],
                              [
                                0.7,
                                -0.72
                              ],
                              [
                                0,
                                0
                              ],
                              [
                                0,
                                0
                              ],
                              [
                                1.06,
                                -1.06
                              ],
                              [
                                0,
                                0
                              ],
                              [
                                1.06,
                                1.06
                              ]
                            ],
                            "v": [
                              [
                                4.225,
                                -1.39
                              ],
                              [
                                1.515,
                                1.32
                              ],
                              [
                                -5.285,
                                8.11
                              ],
                              [
                                -4.145,
                                5.32
                              ],
                              [
                                -4.145,
                                -4.34
                              ],
                              [
                                -1.435,
                                -7.05
                              ],
                              [
                                2.105,
                                -7.05
                              ],
                              [
                                4.225,
                                -4.93
                              ]
                            ],
                            "c": true
                          }
                        ]
                      }
                    ],
                    "ix": 2
                  },
                  "nm": "Path 1",
                  "mn": "ADBE Vector Shape - Group",
                  "hd": false
                },
                {
                  "ty": "st",
                  "c": {
                    "a": 0,
                    "k": [
                      1,
                      1,
                      1,
                      1
                    ],
                    "ix": 3
                  },
                  "o": {
                    "a": 0,
                    "k": 100,
                    "ix": 4
                  },
                  "w": {
                    "a": 0,
                    "k": 1.5,
                    "ix": 5
                  },
                  "lc": 2,
                  "lj": 2,
                  "bm": 0,
                  "nm": "Stroke 1",
                  "mn": "ADBE Vector Graphic - Stroke",
                  "hd": false
                },
                {
                  "ty": "tr",
                  "p": {
                    "a": 0,
                    "k": [
                      13.645,
                      12.18
                    ],
                    "ix": 2
                  },
                  "a": {
                    "a": 0,
                    "k": [
                      0,
                      0
                    ],
                    "ix": 1
                  },
                  "s": {
                    "a": 0,
                    "k": [
                      100,
                      100
                    ],
                    "ix": 3
                  },
                  "r": {
                    "a": 0,
                    "k": 0,
                    "ix": 6
                  },
                  "o": {
                    "a": 0,
                    "k": 100,
                    "ix": 7
                  },
                  "sk": {
                    "a": 0,
                    "k": 0,
                    "ix": 4
                  },
                  "sa": {
                    "a": 0,
                    "k": 0,
                    "ix": 5
                  },
                  "nm": "Transform"
                }
              ],
              "nm": "Group 2",
              "np": 2,
              "cix": 2,
              "bm": 0,
              "ix": 2,
              "mn": "ADBE Vector Group",
              "hd": false
            },
            {
              "ty": "gr",
              "it": [
                {
                  "ind": 0,
                  "ty": "sh",
                  "ix": 1,
                  "ks": {
                    "a": 0,
                    "k": {
                      "i": [
                        [
                          -1.25,
                          -0.39
                        ],
                        [
                          0.47,
                          0.48
                        ],
                        [
                          0.18,
                          0.6
                        ]
                      ],
                      "o": [
                        [
                          -0.6,
                          -0.18
                        ],
                        [
                          -0.48,
                          -0.47
                        ],
                        [
                          0.39,
                          1.25
                        ]
                      ],
                      "v": [
                        [
                          1.315,
                          1.315
                        ],
                        [
                          -0.325,
                          0.325
                        ],
                        [
                          -1.315,
                          -1.315
                        ]
                      ],
                      "c": true
                    },
                    "ix": 2
                  },
                  "nm": "Path 1",
                  "mn": "ADBE Vector Shape - Group",
                  "hd": false
                },
                {
                  "ty": "st",
                  "c": {
                    "a": 0,
                    "k": [
                      1,
                      1,
                      1,
                      1
                    ],
                    "ix": 3
                  },
                  "o": {
                    "a": 0,
                    "k": 100,
                    "ix": 4
                  },
                  "w": {
                    "a": 0,
                    "k": 1.5,
                    "ix": 5
                  },
                  "lc": 2,
                  "lj": 2,
                  "bm": 0,
                  "nm": "Stroke 1",
                  "mn": "ADBE Vector Graphic - Stroke",
                  "hd": false
                },
                {
                  "ty": "tr",
                  "p": {
                    "a": 0,
                    "k": [
                      2.995,
                      20.005
                    ],
                    "ix": 2
                  },
                  "a": {
                    "a": 0,
                    "k": [
                      0,
                      0
                    ],
                    "ix": 1
                  },
                  "s": {
                    "a": 0,
                    "k": [
                      100,
                      100
                    ],
                    "ix": 3
                  },
                  "r": {
                    "a": 0,
                    "k": 0,
                    "ix": 6
                  },
                  "o": {
                    "a": 0,
                    "k": 100,
                    "ix": 7
                  },
                  "sk": {
                    "a": 0,
                    "k": 0,
                    "ix": 4
                  },
                  "sa": {
                    "a": 0,
                    "k": 0,
                    "ix": 5
                  },
                  "nm": "Transform"
                }
              ],
              "nm": "Group 3",
              "np": 2,
              "cix": 2,
              "bm": 0,
              "ix": 3,
              "mn": "ADBE Vector Group",
              "hd": false
            },
            {
              "ty": "gr",
              "it": [
                {
                  "ind": 0,
                  "ty": "sh",
                  "ix": 1,
                  "ks": {
                    "a": 1,
                    "k": [
                      {
                        "i": {
                          "x": 0.65,
                          "y": 1
                        },
                        "o": {
                          "x": 0.35,
                          "y": 0
                        },
                        "t": 7.193,
                        "s": [
                          {
                            "i": [
                              [
                                0,
                                -1.5
                              ],
                              [
                                0,
                                0
                              ],
                              [
                                1.5,
                                0
                              ],
                              [
                                0,
                                0
                              ],
                              [
                                -0.39,
                                0.13
                              ],
                              [
                                -0.11,
                                0.05
                              ],
                              [
                                -0.3,
                                0.26
                              ],
                              [
                                -0.09,
                                0.09
                              ],
                              [
                                0,
                                0
                              ],
                              [
                                0,
                                0
                              ],
                              [
                                0,
                                0
                              ]
                            ],
                            "o": [
                              [
                                0,
                                0
                              ],
                              [
                                0,
                                1.5
                              ],
                              [
                                0,
                                0
                              ],
                              [
                                0.41,
                                0
                              ],
                              [
                                0.11,
                                -0.04
                              ],
                              [
                                0.35,
                                -0.14
                              ],
                              [
                                0.09,
                                -0.07
                              ],
                              [
                                0,
                                0
                              ],
                              [
                                0,
                                0
                              ],
                              [
                                0,
                                0
                              ],
                              [
                                1.5,
                                0
                              ]
                            ],
                            "v": [
                              [
                                8,
                                -1.5
                              ],
                              [
                                8,
                                1.5
                              ],
                              [
                                5.5,
                                4
                              ],
                              [
                                -8,
                                4
                              ],
                              [
                                -6.78,
                                3.81
                              ],
                              [
                                -6.45,
                                3.68
                              ],
                              [
                                -5.46,
                                3.08
                              ],
                              [
                                -5.18,
                                2.83
                              ],
                              [
                                -5.14,
                                2.79
                              ],
                              [
                                1.66,
                                -4
                              ],
                              [
                                5.5,
                                -4
                              ]
                            ],
                            "c": true
                          }
                        ]
                      },
                      {
                        "i": {
                          "x": 0.65,
                          "y": 1
                        },
                        "o": {
                          "x": 0.35,
                          "y": 0
                        },
                        "t": 19.181,
                        "s": [
                          {
                            "i": [
                              [
                                -0.663,
                                -1.115
                              ],
                              [
                                0,
                                0
                              ],
                              [
                                1.771,
                                -0.887
                              ],
                              [
                                0,
                                0
                              ],
                              [
                                -0.39,
                                0.13
                              ],
                              [
                                -0.11,
                                0.05
                              ],
                              [
                                -0.3,
                                0.26
                              ],
                              [
                                -0.09,
                                0.09
                              ],
                              [
                                0,
                                0
                              ],
                              [
                                0,
                                0
                              ],
                              [
                                0,
                                0
                              ]
                            ],
                            "o": [
                              [
                                0,
                                0
                              ],
                              [
                                0.663,
                                1.115
                              ],
                              [
                                0,
                                0
                              ],
                              [
                                0.41,
                                0
                              ],
                              [
                                0.11,
                                -0.04
                              ],
                              [
                                0.35,
                                -0.14
                              ],
                              [
                                0.09,
                                -0.07
                              ],
                              [
                                0,
                                0
                              ],
                              [
                                0,
                                0
                              ],
                              [
                                0,
                                0
                              ],
                              [
                                1.219,
                                -0.874
                              ]
                            ],
                            "v": [
                              [
                                4.675,
                                -6.836
                              ],
                              [
                                6.002,
                                -4.606
                              ],
                              [
                                4.132,
                                -0.588
                              ],
                              [
                                -8,
                                4
                              ],
                              [
                                -6.78,
                                3.81
                              ],
                              [
                                -6.45,
                                3.68
                              ],
                              [
                                -5.46,
                                3.08
                              ],
                              [
                                -5.18,
                                2.83
                              ],
                              [
                                -5.14,
                                2.79
                              ],
                              [
                                -0.423,
                                -4.54
                              ],
                              [
                                1.398,
                                -7.307
                              ]
                            ],
                            "c": true
                          }
                        ]
                      },
                      {
                        "t": 28.771251171877,
                        "s": [
                          {
                            "i": [
                              [
                                0,
                                -1.5
                              ],
                              [
                                0,
                                0
                              ],
                              [
                                1.5,
                                0
                              ],
                              [
                                0,
                                0
                              ],
                              [
                                -0.39,
                                0.13
                              ],
                              [
                                -0.11,
                                0.05
                              ],
                              [
                                -0.3,
                                0.26
                              ],
                              [
                                -0.09,
                                0.09
                              ],
                              [
                                0,
                                0
                              ],
                              [
                                0,
                                0
                              ],
                              [
                                0,
                                0
                              ]
                            ],
                            "o": [
                              [
                                0,
                                0
                              ],
                              [
                                0,
                                1.5
                              ],
                              [
                                0,
                                0
                              ],
                              [
                                0.41,
                                0
                              ],
                              [
                                0.11,
                                -0.04
                              ],
                              [
                                0.35,
                                -0.14
                              ],
                              [
                                0.09,
                                -0.07
                              ],
                              [
                                0,
                                0
                              ],
                              [
                                0,
                                0
                              ],
                              [
                                0,
                                0
                              ],
                              [
                                1.5,
                                0
                              ]
                            ],
                            "v": [
                              [
                                8,
                                -1.5
                              ],
                              [
                                8,
                                1.5
                              ],
                              [
                                5.5,
                                4
                              ],
                              [
                                -8,
                                4
                              ],
                              [
                                -6.78,
                                3.81
                              ],
                              [
                                -6.45,
                                3.68
                              ],
                              [
                                -5.46,
                                3.08
                              ],
                              [
                                -5.18,
                                2.83
                              ],
                              [
                                -5.14,
                                2.79
                              ],
                              [
                                1.66,
                                -4
                              ],
                              [
                                5.5,
                                -4
                              ]
                            ],
                            "c": true
                          }
                        ]
                      }
                    ],
                    "ix": 2
                  },
                  "nm": "Path 1",
                  "mn": "ADBE Vector Shape - Group",
                  "hd": false
                },
                {
                  "ty": "st",
                  "c": {
                    "a": 0,
                    "k": [
                      1,
                      1,
                      1,
                      1
                    ],
                    "ix": 3
                  },
                  "o": {
                    "a": 0,
                    "k": 100,
                    "ix": 4
                  },
                  "w": {
                    "a": 0,
                    "k": 1.5,
                    "ix": 5
                  },
                  "lc": 2,
                  "lj": 2,
                  "bm": 0,
                  "nm": "Stroke 1",
                  "mn": "ADBE Vector Graphic - Stroke",
                  "hd": false
                },
                {
                  "ty": "tr",
                  "p": {
                    "a": 0,
                    "k": [
                      13.5,
                      17.5
                    ],
                    "ix": 2
                  },
                  "a": {
                    "a": 0,
                    "k": [
                      0,
                      0
                    ],
                    "ix": 1
                  },
                  "s": {
                    "a": 0,
                    "k": [
                      100,
                      100
                    ],
                    "ix": 3
                  },
                  "r": {
                    "a": 0,
                    "k": 0,
                    "ix": 6
                  },
                  "o": {
                    "a": 0,
                    "k": 100,
                    "ix": 7
                  },
                  "sk": {
                    "a": 0,
                    "k": 0,
                    "ix": 4
                  },
                  "sa": {
                    "a": 0,
                    "k": 0,
                    "ix": 5
                  },
                  "nm": "Transform"
                }
              ],
              "nm": "Group 4",
              "np": 2,
              "cix": 2,
              "bm": 0,
              "ix": 4,
              "mn": "ADBE Vector Group",
              "hd": false
            },
            {
              "ty": "gr",
              "it": [
                {
                  "ind": 0,
                  "ty": "sh",
                  "ix": 1,
                  "ks": {
                    "a": 0,
                    "k": {
                      "i": [
                        [
                          0,
                          -1.5
                        ],
                        [
                          0,
                          0
                        ],
                        [
                          0.7,
                          -0.72
                        ],
                        [
                          0,
                          0
                        ],
                        [
                          0.09,
                          -0.07
                        ],
                        [
                          0.35,
                          -0.14
                        ],
                        [
                          0.11,
                          -0.04
                        ],
                        [
                          0.41,
                          0
                        ],
                        [
                          0.26,
                          0.05
                        ],
                        [
                          0.13,
                          0.04
                        ],
                        [
                          0.15,
                          0.07
                        ],
                        [
                          0.01,
                          -0.01
                        ],
                        [
                          0.25,
                          0.19
                        ],
                        [
                          0,
                          0
                        ],
                        [
                          0.11,
                          0.12
                        ],
                        [
                          0.11,
                          0.13
                        ],
                        [
                          0.14,
                          0.28
                        ],
                        [
                          0.01,
                          0
                        ],
                        [
                          0.01,
                          0.01
                        ],
                        [
                          0.05,
                          0.15
                        ],
                        [
                          0.03,
                          0.13
                        ],
                        [
                          0,
                          0.27
                        ],
                        [
                          0,
                          0
                        ],
                        [
                          -1.5,
                          0
                        ],
                        [
                          0,
                          0
                        ]
                      ],
                      "o": [
                        [
                          0,
                          0
                        ],
                        [
                          0,
                          1.08
                        ],
                        [
                          0,
                          0
                        ],
                        [
                          -0.09,
                          0.09
                        ],
                        [
                          -0.3,
                          0.26
                        ],
                        [
                          -0.11,
                          0.05
                        ],
                        [
                          -0.39,
                          0.13
                        ],
                        [
                          -0.27,
                          0
                        ],
                        [
                          -0.13,
                          -0.03
                        ],
                        [
                          -0.16,
                          -0.05
                        ],
                        [
                          0,
                          -0.01
                        ],
                        [
                          -0.28,
                          -0.14
                        ],
                        [
                          0,
                          0
                        ],
                        [
                          -0.13,
                          -0.1
                        ],
                        [
                          -0.11,
                          -0.12
                        ],
                        [
                          -0.19,
                          -0.25
                        ],
                        [
                          0.01,
                          -0.01
                        ],
                        [
                          0,
                          0
                        ],
                        [
                          -0.06,
                          -0.14
                        ],
                        [
                          -0.04,
                          -0.13
                        ],
                        [
                          -0.05,
                          -0.26
                        ],
                        [
                          0,
                          0
                        ],
                        [
                          0,
                          -1.5
                        ],
                        [
                          0,
                          0
                        ],
                        [
                          1.5,
                          0
                        ]
                      ],
                      "v": [
                        [
                          4,
                          -7.5
                        ],
                        [
                          4,
                          6
                        ],
                        [
                          2.86,
                          8.79
                        ],
                        [
                          2.82,
                          8.83
                        ],
                        [
                          2.54,
                          9.08
                        ],
                        [
                          1.55,
                          9.68
                        ],
                        [
                          1.22,
                          9.81
                        ],
                        [
                          0,
                          10
                        ],
                        [
                          -0.8,
                          9.92
                        ],
                        [
                          -1.19,
                          9.82
                        ],
                        [
                          -1.65,
                          9.65
                        ],
                        [
                          -1.66,
                          9.65
                        ],
                        [
                          -2.46,
                          9.16
                        ],
                        [
                          -2.47,
                          9.15
                        ],
                        [
                          -2.83,
                          8.83
                        ],
                        [
                          -3.16,
                          8.46
                        ],
                        [
                          -3.65,
                          7.66
                        ],
                        [
                          -3.65,
                          7.65
                        ],
                        [
                          -3.66,
                          7.63
                        ],
                        [
                          -3.82,
                          7.19
                        ],
                        [
                          -3.92,
                          6.8
                        ],
                        [
                          -4,
                          6
                        ],
                        [
                          -4,
                          -7.5
                        ],
                        [
                          -1.5,
                          -10
                        ],
                        [
                          1.5,
                          -10
                        ]
                      ],
                      "c": true
                    },
                    "ix": 2
                  },
                  "nm": "Path 1",
                  "mn": "ADBE Vector Shape - Group",
                  "hd": false
                },
                {
                  "ty": "st",
                  "c": {
                    "a": 0,
                    "k": [
                      1,
                      1,
                      1,
                      1
                    ],
                    "ix": 3
                  },
                  "o": {
                    "a": 0,
                    "k": 100,
                    "ix": 4
                  },
                  "w": {
                    "a": 0,
                    "k": 1.5,
                    "ix": 5
                  },
                  "lc": 2,
                  "lj": 2,
                  "bm": 0,
                  "nm": "Stroke 1",
                  "mn": "ADBE Vector Graphic - Stroke",
                  "hd": false
                },
                {
                  "ty": "tr",
                  "p": {
                    "a": 0,
                    "k": [
                      5.5,
                      11.5
                    ],
                    "ix": 2
                  },
                  "a": {
                    "a": 0,
                    "k": [
                      0,
                      0
                    ],
                    "ix": 1
                  },
                  "s": {
                    "a": 0,
                    "k": [
                      100,
                      100
                    ],
                    "ix": 3
                  },
                  "r": {
                    "a": 0,
                    "k": 0,
                    "ix": 6
                  },
                  "o": {
                    "a": 0,
                    "k": 100,
                    "ix": 7
                  },
                  "sk": {
                    "a": 0,
                    "k": 0,
                    "ix": 4
                  },
                  "sa": {
                    "a": 0,
                    "k": 0,
                    "ix": 5
                  },
                  "nm": "Transform"
                }
              ],
              "nm": "Group 5",
              "np": 2,
              "cix": 2,
              "bm": 0,
              "ix": 5,
              "mn": "ADBE Vector Group",
              "hd": false
            },
            {
              "ty": "tr",
              "p": {
                "a": 0,
                "k": [
                  6.06,
                  17.519
                ],
                "ix": 2
              },
              "a": {
                "a": 0,
                "k": [
                  6.06,
                  17.519
                ],
                "ix": 1
              },
              "s": {
                "a": 0,
                "k": [
                  100,
                  100
                ],
                "ix": 3
              },
              "r": {
                "a": 1,
                "k": [
                  {
                    "i": {
                      "x": [
                        0.65
                      ],
                      "y": [
                        1
                      ]
                    },
                    "o": {
                      "x": [
                        0.35
                      ],
                      "y": [
                        0
                      ]
                    },
                    "t": 4.795,
                    "s": [
                      0
                    ]
                  },
                  {
                    "i": {
                      "x": [
                        0.833
                      ],
                      "y": [
                        0.833
                      ]
                    },
                    "o": {
                      "x": [
                        0.35
                      ],
                      "y": [
                        0
                      ]
                    },
                    "t": 14.385,
                    "s": [
                      -37
                    ]
                  },
                  {
                    "t": 25.1750010253988,
                    "s": [
                      0
                    ]
                  }
                ],
                "ix": 6,
                "x": "var $bm_rt;\nvar amp, freq, decay, n, n, t, t, v;\ntry {\n    amp = $bm_div(effect('Elastic Controller')(1), 200);\n    freq = $bm_div(effect('Elastic Controller')(2), 30);\n    decay = $bm_div(effect('Elastic Controller')(3), 10);\n    $bm_rt = n = 0;\n    if (numKeys > 0) {\n        $bm_rt = n = nearestKey(time).index;\n        if (key(n).time > time) {\n            n--;\n        }\n    }\n    if (n == 0) {\n        $bm_rt = t = 0;\n    } else {\n        $bm_rt = t = $bm_sub(time, key(n).time);\n    }\n    if (n > 0) {\n        v = velocityAtTime($bm_sub(key(n).time, $bm_div(thisComp.frameDuration, 10)));\n        $bm_rt = $bm_sum(value, $bm_div($bm_mul($bm_mul(v, amp), Math.sin($bm_mul($bm_mul($bm_mul(freq, t), 2), Math.PI))), Math.exp($bm_mul(decay, t))));\n    } else {\n        $bm_rt = value;\n    }\n} catch (e$$4) {\n    $bm_rt = value = value;\n}"
              },
              "o": {
                "a": 0,
                "k": 100,
                "ix": 7
              },
              "sk": {
                "a": 0,
                "k": 0,
                "ix": 4
              },
              "sa": {
                "a": 0,
                "k": 0,
                "ix": 5
              },
              "nm": "Transform"
            }
          ],
          "nm": "Group 1",
          "np": 5,
          "cix": 2,
          "bm": 0,
          "ix": 1,
          "mn": "ADBE Vector Group",
          "hd": false
        }
      ],
      "ip": 0,
      "op": 74.0000030140818,
      "st": 0,
      "bm": 0
    }
  ],
  "markers": []
}